litematica_tools/__init__.py
litematica_tools/errors.py
litematica_tools/material_list.py
litematica_tools/structure_parser.py
litematica_tools/utils.py
litematica_tools/config/__init__.py
litematica_tools/scripts/__init__.py
litematica_tools/scripts/cli.py
litematica_tools/storage/__init__.py
litematica_tools/storage/litematic_storage.py
litematica_tools/storage/nbt_storage.py
litematica_tools/storage/schem_storage.py
litematica_tools/storage/shared_storage.py
litematica_tools-1.0.2.dist-info/LICENSE
litematica_tools-1.0.2.dist-info/METADATA
litematica_tools-1.0.2.dist-info/WHEEL
litematica_tools-1.0.2.dist-info/top_level.txt
litematica_tools-1.0.2.dist-info/RECORD
