Metadata-Version: 2.1
Name: litematica-tools
Version: 1.0.2
Summary: Python scripts for interacting with litematica and other formats
Home-page: https://github.com/Kikugie/litematica-tools
Author: KikuGie
Author-email: kikugie@duck.com
License: UNKNOWN
Project-URL: Bug Tracker, https://github.com/Kikugie/litematica-tools/issues
Platform: UNKNOWN
Classifier: Programming Language :: Python :: 3
Classifier: License :: OSI Approved :: MIT License
Classifier: Operating System :: OS Independent
Requires-Python: >=3.10
License-File: LICENSE
Requires-Dist: nbtlib
